CHANGELOG.md
LICENSE
README.md
sutoppu.py
sutoppu-1.2.0.dist-info/LICENSE
sutoppu-1.2.0.dist-info/METADATA
sutoppu-1.2.0.dist-info/WHEEL
sutoppu-1.2.0.dist-info/RECORD
