Metadata-Version: 2.1
Name: sutoppu
Version: 1.2.0
Summary: A simple python implementation of Specification pattern.
Home-page: https://github.com/u8slvn/sutoppu
License: MIT
Keywords: specification,specification-pattern,DDD,domain-driven-design,business-rules,verification
Author: u8slvn
Author-email: u8slvn@gmail.com
Requires-Python: >=3.8.1,<4.0.0
Classifier: Development Status :: 5 - Production/Stable
Classifier: Intended Audience :: Developers
Classifier: License :: OSI Approved :: MIT License
Classifier: Natural Language :: English
Classifier: Operating System :: OS Independent
Classifier: Programming Language :: Python
Classifier: Programming Language :: Python :: 3
Classifier: Programming Language :: Python :: 3.9
Classifier: Programming Language :: Python :: 3.10
Classifier: Programming Language :: Python :: 3.11
Classifier: Programming Language :: Python :: 3.12
Classifier: Topic :: Software Development :: Build Tools
Classifier: Topic :: Software Development :: Libraries :: Python Modules
Classifier: Topic :: Software Development :: Testing
Requires-Dist: typing-extensions (>=4.0.0) ; python_version < "3.11"
Project-URL: Repository, https://github.com/u8slvn/sutoppu
